anubis/__init__.py
anubis/main.py
anubis/tasks/__init__.py
anubis/tasks/airflow.py
anubis/tasks/aws.py
anubis/tasks/bitwarden.py
anubis/tasks/check.py
anubis/tasks/docker.py
anubis/tasks/misc.py
anubis/utils.py
anubis_cli-0.0.18.dist-info/METADATA
anubis_cli-0.0.18.dist-info/WHEEL
anubis_cli-0.0.18.dist-info/entry_points.txt
anubis_cli-0.0.18.dist-info/licenses/LICENSE
anubis_cli-0.0.18.dist-info/RECORD
