Metadata-Version: 2.1
Name: anubis-cli
Version: 0.0.18
Summary: Sbayt Anubis CLI
Author-Email: Sbayt <info@sbayt.ai>
License: MIT
Classifier: Development Status :: 5 - Production/Stable
Classifier: License :: OSI Approved :: MIT License
Classifier: Intended Audience :: Developers
Classifier: Programming Language :: Python :: 3 :: Only
Classifier: Programming Language :: Python :: 3.10
Classifier: Programming Language :: Python :: 3.11
Classifier: Programming Language :: Python :: 3.12
Project-URL: Documentation, https://github.com/Steel-Develop/sbayt-cli-anubis/tree/master#readme
Project-URL: Homepage, https://github.com/Steel-Develop/sbayt-cli-anubis
Project-URL: Issues, https://steeldevelop.atlassian.net/
Requires-Python: >=3.10
Requires-Dist: invoke>=2.2.0
Requires-Dist: jinja2>=3.1.6
Requires-Dist: pyyaml>=6.0.2
Requires-Dist: rich>=14.0.0
Requires-Dist: uv>=0.7.0
